<?xml version="1.0" encoding="UTF-8"?>
<legiscan><status></status><bill><bill_id>396327</bill_id><change_hash>c703687992bdbbb8f2d482f80f1473af</change_hash><session><session_id>476</session_id><session_name>2012 Regular Session</session_name></session><url>http://legiscan.com/MS/bill/HB231/2012</url><state_link>http://billstatus.ls.state.ms.us/2012/pdf/history/HB/HB0231.xml</state_link><completed>1</completed><status>6</status><status_date>2012-03-06</status_date><progress><step><date>2012-02-13</date><event>1</event></step><step><date>2012-02-13</date><event>9</event></step><step><date>2012-03-06</date><event>6</event></step></progress><state>MS</state><state_id>24</state_id><bill_number>HB231</bill_number><bill_type>B</bill_type><body>H</body><body_id>57</body_id><current_body>H</current_body><current_body_id>57</current_body_id><title>Hope Program; establish and develop system to re-enroll high school dropouts in programs leading to a high school diploma.</title><description>An Act To Establish The Hope And Opportunity Pathways Through Education (hope) Program, Which Shall Be Implemented And Administered By The State Department Of Education; To Provide That The Goal Of The Hope Program Is To Develop A Comprehensive System In This State To Re-enroll Significant Numbers Of High School Dropouts In Programs That Will Enable Them To Earn Their High School Diploma; To Provide That The Hope Program Shall Award Grants, Subject To Appropriation For That Purpose, To School Districts To Assist In Establishing Instructional Programs And Other Services Designed To Re-enroll High School Dropouts; To Require A Student In The Hope Program Who Wishes To Earn A High School Diploma To Meet The Prerequisites To Receiving A High School Diploma And Any Other Graduation Requirements Of The Student's District Of Residence; To Provide That Any Student Who Successfully Completes The Requirements For Graduation Shall Receive A Diploma Identifying The Student As Graduating From The Students District Of Residence; To Provide That In Order To Be Eligible For Funding, A School District Must Develop A Hope Plan To Be Approved By The State Board Of Education; To Provide That A School District May Operate Its Own Program Or Enter Into A Contract With Other Not-for-profit Entities To Operate A Program; To Provide That Hope Program Funding Must Be Distributed Based Upon The Proportion Of Dropouts In The School District To The Total Number Of Dropouts In This State; To Provide That A School District May Receive Adequate Education Program Funds For Students Enrolled In A Hope Program If Certain Criteria Are Met; To Specify Categories Of Programming In The Hope Program; To Specify The Minimum Components For Programs To Be Funded Through The Hope Program; And For Related Purposes.</description><committee/><history><step><date>2012-02-13</date><action>Referred To Education;Appropriations</action><chamber></chamber><chamber_id>0</chamber_id><importance>1</importance></step><step><date>2012-03-06</date><action>Died In Committee</action><chamber></chamber><chamber_id>0</chamber_id><importance>1</importance></step></history><sponsors><sponsor><people_id>6524</people_id><name>Omeria Scott</name><role_id>1</role_id><ftm_id>0</ftm_id><sponsor_type_id>0</sponsor_type_id><sponsor_order>0</sponsor_order></sponsor></sponsors><texts><text><doc_id>573582</doc_id><date>2012-02-13</date><type>Introduced</type><mime>text/html</mime><url>http://legiscan.com/MS/text/HB231/id/573582</url><state_link>http://billstatus.ls.state.ms.us/documents/2012/html/HB/0200-0299/HB0231IN.htm</state_link></text></texts></bill></legiscan>
