<?xml version="1.0" encoding="UTF-8"?>
<legiscan><status></status><bill><bill_id>147641</bill_id><change_hash>855da027c135dee35a605d7dbb938c99</change_hash><session><session_id>44</session_id><session_name>2010 Regular Session</session_name></session><url>http://legiscan.com/MS/bill/SB2646/2010</url><state_link>http://billstatus.ls.state.ms.us/2010/pdf/history/SB/SB2646.xml</state_link><completed>0</completed><status>4</status><status_date>2010-04-14</status_date><progress><step><date>2010-01-14</date><event>1</event></step><step><date>2010-01-14</date><event>9</event></step><step><date>2010-02-11</date><event>2</event></step><step><date>2010-02-17</date><event>9</event></step><step><date>2010-03-31</date><event>3</event></step><step><date>2010-04-14</date><event>4</event></step></progress><state>MS</state><state_id>24</state_id><bill_number>SB2646</bill_number><bill_type>B</bill_type><body>S</body><body_id>58</body_id><current_body>H</current_body><current_body_id>57</current_body_id><title>State Employee Wellness Program; establish.</title><description>An Act To Create A State Employee Wellness Program; To Provide For Definitions; To Establish Standards For The Wellness Program; To Authorize State Agencies To Participate In The State Employee Wellness Program; To Repeal Sections 41-97-1 Through 41-97-7, Mississippi Code Of 1972, Which Authorize State Agencies To Establish Employee Volunteer Wellness And Physical Fitness Programs, Prescribe The Duties Of Agencies Establishing Those Programs, And Require The State Board Of Health To Administer And Approve Those Programs; And For Related Purposes.</description><committee/><history><step><date>2010-01-14</date><action>Referred To Public Health and Welfare;Appropriations</action><chamber></chamber><chamber_id>0</chamber_id><importance>1</importance></step><step><date>2010-02-02</date><action>DR - TSDP: PH To AP</action><chamber></chamber><chamber_id>0</chamber_id><importance>0</importance></step><step><date>2010-02-02</date><action>DR - TSDPCS: AP To PH</action><chamber></chamber><chamber_id>0</chamber_id><importance>0</importance></step><step><date>2010-02-02</date><action>Title Suff Do Pass Comm Sub</action><chamber></chamber><chamber_id>0</chamber_id><importance>0</importance></step><step><date>2010-02-11</date><action>Committee Substitute Adopted</action><chamber></chamber><chamber_id>0</chamber_id><importance>0</importance></step><step><date>2010-02-11</date><action>Passed</action><chamber></chamber><chamber_id>0</chamber_id><importance>1</importance></step><step><date>2010-02-16</date><action>Transmitted To House</action><chamber></chamber><chamber_id>0</chamber_id><importance>0</importance></step><step><date>2010-02-17</date><action>Referred To Public Health and Human Services;Appropriations</action><chamber></chamber><chamber_id>0</chamber_id><importance>1</importance></step><step><date>2010-02-25</date><action>DR - TSDP: PH To AP</action><chamber></chamber><chamber_id>0</chamber_id><importance>0</importance></step><step><date>2010-03-02</date><action>DR - TSDP: AP To PH</action><chamber></chamber><chamber_id>0</chamber_id><importance>0</importance></step><step><date>2010-03-02</date><action>Title Suff Do Pass</action><chamber></chamber><chamber_id>0</chamber_id><importance>0</importance></step><step><date>2010-03-09</date><action>Amended</action><chamber></chamber><chamber_id>0</chamber_id><importance>0</importance></step><step><date>2010-03-09</date><action>Passed As Amended</action><chamber></chamber><chamber_id>0</chamber_id><importance>0</importance></step><step><date>2010-03-10</date><action>Returned For Concurrence</action><chamber></chamber><chamber_id>0</chamber_id><importance>0</importance></step><step><date>2010-03-16</date><action>Decline to Concur/Invite Conf</action><chamber></chamber><chamber_id>0</chamber_id><importance>0</importance></step><step><date>2010-03-22</date><action>Conferees Named Bryan,Dearing,Jones</action><chamber></chamber><chamber_id>0</chamber_id><importance>0</importance></step><step><date>2010-03-24</date><action>Conferees Named Holland,Moak,Stringer</action><chamber></chamber><chamber_id>0</chamber_id><importance>0</importance></step><step><date>2010-03-24</date><action>Conference Report Filed</action><chamber></chamber><chamber_id>0</chamber_id><importance>0</importance></step><step><date>2010-03-24</date><action>Conference Report Filed</action><chamber></chamber><chamber_id>0</chamber_id><importance>0</importance></step><step><date>2010-03-25</date><action>Conference Report Adopted</action><chamber></chamber><chamber_id>0</chamber_id><importance>0</importance></step><step><date>2010-03-25</date><action>Conference Report Adopted</action><chamber></chamber><chamber_id>0</chamber_id><importance>0</importance></step><step><date>2010-03-31</date><action>Enrolled Bill Signed</action><chamber></chamber><chamber_id>0</chamber_id><importance>1</importance></step><step><date>2010-04-07</date><action>Enrolled Bill Signed</action><chamber></chamber><chamber_id>0</chamber_id><importance>0</importance></step><step><date>2010-04-14</date><action>Approved by Governor</action><chamber></chamber><chamber_id>0</chamber_id><importance>1</importance></step></history><sponsors><sponsor><people_id>6614</people_id><name>Chris McDaniel</name><role_id>2</role_id><ftm_id>9012</ftm_id><sponsor_type_id>0</sponsor_type_id><sponsor_order>0</sponsor_order></sponsor><sponsor><people_id>6658</people_id><name>Hillman Frazier</name><role_id>2</role_id><ftm_id>0</ftm_id><sponsor_type_id>0</sponsor_type_id><sponsor_order>0</sponsor_order></sponsor><sponsor><people_id>6655</people_id><name>Kenneth Jones</name><role_id>2</role_id><ftm_id>0</ftm_id><sponsor_type_id>0</sponsor_type_id><sponsor_order>0</sponsor_order></sponsor><sponsor><people_id>6652</people_id><name>Robert Jackson</name><role_id>2</role_id><ftm_id>0</ftm_id><sponsor_type_id>0</sponsor_type_id><sponsor_order>0</sponsor_order></sponsor><sponsor><people_id>6649</people_id><name>Nolan Mettetal</name><role_id>1</role_id><ftm_id>2249</ftm_id><sponsor_type_id>0</sponsor_type_id><sponsor_order>0</sponsor_order></sponsor><sponsor><people_id>6648</people_id><name>Sampson Jackson</name><role_id>2</role_id><ftm_id>0</ftm_id><sponsor_type_id>0</sponsor_type_id><sponsor_order>0</sponsor_order></sponsor><sponsor><people_id>6643</people_id><name>David Baria</name><role_id>1</role_id><ftm_id>0</ftm_id><sponsor_type_id>0</sponsor_type_id><sponsor_order>0</sponsor_order></sponsor><sponsor><people_id>6640</people_id><name>Tom King</name><role_id>2</role_id><ftm_id>0</ftm_id><sponsor_type_id>0</sponsor_type_id><sponsor_order>0</sponsor_order></sponsor><sponsor><people_id>6639</people_id><name>Terry Burton</name><role_id>2</role_id><ftm_id>0</ftm_id><sponsor_type_id>0</sponsor_type_id><sponsor_order>0</sponsor_order></sponsor><sponsor><people_id>6635</people_id><name>Johnnie Walls</name><role_id>2</role_id><ftm_id>374</ftm_id><sponsor_type_id>0</sponsor_type_id><sponsor_order>0</sponsor_order></sponsor><sponsor><people_id>6634</people_id><name>David Jordan</name><role_id>2</role_id><ftm_id>0</ftm_id><sponsor_type_id>0</sponsor_type_id><sponsor_order>0</sponsor_order></sponsor><sponsor><people_id>6633</people_id><name>Gary Jackson</name><role_id>2</role_id><ftm_id>0</ftm_id><sponsor_type_id>0</sponsor_type_id><sponsor_order>0</sponsor_order></sponsor><sponsor><people_id>6630</people_id><name>Alice Harden</name><role_id>2</role_id><ftm_id>380</ftm_id><sponsor_type_id>0</sponsor_type_id><sponsor_order>0</sponsor_order></sponsor><sponsor><people_id>6628</people_id><name>Kelvin Butler</name><role_id>2</role_id><ftm_id>0</ftm_id><sponsor_type_id>0</sponsor_type_id><sponsor_order>0</sponsor_order></sponsor><sponsor><people_id>6626</people_id><name>David Blount</name><role_id>2</role_id><ftm_id>9011</ftm_id><sponsor_type_id>0</sponsor_type_id><sponsor_order>0</sponsor_order></sponsor><sponsor><people_id>6620</people_id><name>Bob Dearing</name><role_id>2</role_id><ftm_id>387</ftm_id><sponsor_type_id>0</sponsor_type_id><sponsor_order>0</sponsor_order></sponsor><sponsor><people_id>6617</people_id><name>Lee Yancey</name><role_id>2</role_id><ftm_id>9010</ftm_id><sponsor_type_id>0</sponsor_type_id><sponsor_order>0</sponsor_order></sponsor><sponsor><people_id>6659</people_id><name>Jack Gordon</name><role_id>2</role_id><ftm_id>0</ftm_id><sponsor_type_id>0</sponsor_type_id><sponsor_order>0</sponsor_order></sponsor></sponsors><texts><text><doc_id>422365</doc_id><date>2010-03-15</date><type>Introduced</type><mime>text/html</mime><url>http://legiscan.com/MS/text/SB2646/id/422365</url><state_link>http://billstatus.ls.state.ms.us/documents/2010/html/SB/2600-2699/SB2646IN.htm</state_link></text><text><doc_id>422366</doc_id><date>2010-03-15</date><type>Comm Sub</type><mime>text/html</mime><url>http://legiscan.com/MS/text/SB2646/id/422366</url><state_link>http://billstatus.ls.state.ms.us/documents/2010/html/SB/2600-2699/SB2646CS.htm</state_link></text><text><doc_id>422367</doc_id><date>2010-03-27</date><type>Engrossed</type><mime>text/html</mime><url>http://legiscan.com/MS/text/SB2646/id/422367</url><state_link>http://billstatus.ls.state.ms.us/documents/2010/html/SB/2600-2699/SB2646PS.htm</state_link></text><text><doc_id>422368</doc_id><date>2010-03-31</date><type>Enrolled</type><mime>text/html</mime><url>http://legiscan.com/MS/text/SB2646/id/422368</url><state_link>http://billstatus.ls.state.ms.us/documents/2010/html/SB/2600-2699/SB2646SG.htm</state_link></text></texts><votes><vote><roll_call_id>120406</roll_call_id><date>2010-02-11</date><passed>1</passed><desc>Senate Passed</desc><url>http://legiscan.com/MS/rollcall/SB2646/id/120406</url><state_link>http://billstatus.ls.state.ms.us/2010/pdf/votes/senate/0380021.pdf</state_link></vote><vote><roll_call_id>120407</roll_call_id><date>2010-03-09</date><passed>1</passed><desc>House Passed As Amended</desc><url>http://legiscan.com/MS/rollcall/SB2646/id/120407</url><state_link>http://billstatus.ls.state.ms.us/2010/pdf/votes/house/0640005.pdf</state_link></vote><vote><roll_call_id>120408</roll_call_id><date>2010-03-25</date><passed>1</passed><desc>House Conference Report Adopted</desc><url>http://legiscan.com/MS/rollcall/SB2646/id/120408</url><state_link>http://billstatus.ls.state.ms.us/2010/pdf/votes/house/0800016.pdf</state_link></vote><vote><roll_call_id>120409</roll_call_id><date>2010-03-25</date><passed>1</passed><desc>Senate Conference Report Adopted</desc><url>http://legiscan.com/MS/rollcall/SB2646/id/120409</url><state_link>http://billstatus.ls.state.ms.us/2010/pdf/votes/senate/0800026.pdf</state_link></vote></votes></bill></legiscan>
