<?xml version="1.0" encoding="UTF-8"?>
<legiscan><status></status><bill><bill_id>148172</bill_id><change_hash>780870b1d7a11bd1c8de96f843a66203</change_hash><session><session_id>44</session_id><session_name>2010 Regular Session</session_name></session><url>http://legiscan.com/MS/bill/SB3177/2010</url><state_link>http://billstatus.ls.state.ms.us/2010/pdf/history/SB/SB3177.xml</state_link><completed>1</completed><status>6</status><status_date>2010-02-24</status_date><progress><step><date>2010-02-17</date><event>1</event></step><step><date>2010-02-17</date><event>9</event></step><step><date>2010-02-24</date><event>6</event></step></progress><state>MS</state><state_id>24</state_id><bill_number>SB3177</bill_number><bill_type>B</bill_type><body>S</body><body_id>58</body_id><current_body>S</current_body><current_body_id>58</current_body_id><title>Bonds; authorize issuance for the Water Pollution Control Revolving Fund.</title><description>An Act To Authorize The Issuance Of State General Obligation Bonds In The Amount Of $2,470,000.00 To Provide Matching Funds For Federal Funds For The Water Pollution Control Revolving Fund; To Amend Section 49-17-85, Mississippi Code Of 1972, To Authorize Interest And Investment Earnings On Money In The Water Pollution Control Revolving Fund To Be Utilized To Pay Debt Service On The Bonds Authorized To Be Issued By This Act; And For Related Purposes.</description><committee/><history><step><date>2010-02-17</date><action>Referred To Finance</action><chamber></chamber><chamber_id>0</chamber_id><importance>1</importance></step><step><date>2010-02-24</date><action>Died In Committee</action><chamber></chamber><chamber_id>0</chamber_id><importance>1</importance></step></history><sponsors><sponsor><people_id>6650</people_id><name>T.O. Moffatt</name><role_id>2</role_id><ftm_id>2254</ftm_id><sponsor_type_id>0</sponsor_type_id><sponsor_order>0</sponsor_order></sponsor></sponsors><texts><text><doc_id>383736</doc_id><date>2010-03-15</date><type>Introduced</type><mime>text/html</mime><url>http://legiscan.com/MS/text/SB3177/id/383736</url><state_link>http://billstatus.ls.state.ms.us/documents/2010/html/SB/3100-3199/SB3177IN.htm</state_link></text></texts></bill></legiscan>
