<?xml version="1.0" encoding="UTF-8"?>
<legiscan><status></status><bill><bill_id>473881</bill_id><change_hash>d77d26b7082b507937895605a3c0a255</change_hash><session><session_id>1008</session_id><session_name>2013 Regular Session</session_name></session><url>http://legiscan.com/MS/bill/SB2649/2013</url><state_link>http://billstatus.ls.state.ms.us/2013/pdf/history/SB/SB2649.xml</state_link><completed>1</completed><status>6</status><status_date>2013-02-05</status_date><progress><step><date>2013-01-21</date><event>1</event></step><step><date>2013-01-21</date><event>9</event></step><step><date>2013-02-05</date><event>6</event></step></progress><state>MS</state><state_id>24</state_id><bill_number>SB2649</bill_number><bill_type>B</bill_type><body>S</body><body_id>58</body_id><current_body>S</current_body><current_body_id>58</current_body_id><title>Adoption; expedited for readoptions of foreign-born adoptees.</title><description>An Act To Amend Sections 93-17-3, 93-17-13 And 93-17-14, Mississippi Code Of 1972, To Authorize Expedited Pro Se Proceedings For Registration Of Foreign Adoptions And Issuance Of A Mississippi Birth Certificate Under Certain Circumstances; To Create Sections 97-17-301, 97-17-303, 97-17-305 And 97-17-307, Mississippi Code Of 1972, To Create Title 97, Chapter 17, Article 9, To Constitute The Mississippi Registration Of Foreign Adoption Act; And For Related Purposes.</description><committee/><history><step><date>2013-01-21</date><action>Referred To Judiciary, Division A</action><chamber>S</chamber><chamber_id>58</chamber_id><importance>1</importance></step><step><date>2013-02-05</date><action>Died In Committee</action><chamber>S</chamber><chamber_id>58</chamber_id><importance>1</importance></step></history><sponsors><sponsor><people_id>6631</people_id><name>Billy Hudson</name><role_id>2</role_id><ftm_id>0</ftm_id><sponsor_type_id>1</sponsor_type_id><sponsor_order>1</sponsor_order></sponsor><sponsor><people_id>6657</people_id><name>Perry Lee</name><role_id>2</role_id><ftm_id>0</ftm_id><sponsor_type_id>1</sponsor_type_id><sponsor_order>2</sponsor_order></sponsor><sponsor><people_id>13660</people_id><name>Phillip Gandy</name><role_id>2</role_id><ftm_id>0</ftm_id><sponsor_type_id>1</sponsor_type_id><sponsor_order>3</sponsor_order></sponsor></sponsors><texts><text><doc_id>707192</doc_id><date>2013-01-25</date><type>Introduced</type><mime>text/html</mime><url>http://legiscan.com/MS/text/SB2649/id/707192</url><state_link>http://billstatus.ls.state.ms.us/documents/2013/html/SB/2600-2699/SB2649IN.htm</state_link></text></texts></bill></legiscan>
