<?xml version="1.0" encoding="UTF-8"?>
<legiscan><status></status><bill><bill_id>583422</bill_id><change_hash>97ee484d00f56c170d7a79679b28f550</change_hash><session><session_id>1083</session_id><session_name>2014 Regular Session</session_name></session><url>http://legiscan.com/MS/bill/HB151/2014</url><state_link>http://billstatus.ls.state.ms.us/2014/pdf/history/HB/HB0151.xml</state_link><completed>1</completed><status>6</status><status_date>2014-02-04</status_date><progress><step><date>2014-01-13</date><event>1</event></step><step><date>2014-01-13</date><event>9</event></step><step><date>2014-02-04</date><event>6</event></step></progress><state>MS</state><state_id>24</state_id><bill_number>HB151</bill_number><bill_type>B</bill_type><body>H</body><body_id>57</body_id><current_body>H</current_body><current_body_id>57</current_body_id><title>Hope Program; establish and develop system to re-enroll high school dropouts in programs leading to a high school diploma.</title><description>An Act To Establish The Hope And Opportunity Pathways Through Education (hope) Program, To Be Administered By The State Department Of Education; To Provide That The Goal Of The Hope Program Is To Develop A Comprehensive System To Re-enroll High School Dropouts In Programs That Will Enable Them To Earn Their High School Diploma; To Provide That The Hope Program Shall Award Grants To School Districts To Assist In Establishing Instructional Programs And Other Services Designed To Re-enroll High School Dropouts; To Require A Student In The Hope Program Who Wishes To Earn A High School Diploma To Meet The Graduation Requirements Of The Student's District Of Residence; To Provide That In Order To Be Eligible For Funding, A School District Must Develop A Hope Plan Approved By The State Board Of Education; To Provide That A School District May Operate Its Own Program Or Enter Into A Contract With Other Not-for-profit Entities To Operate A Program; To Provide That Hope Program Funding Must Be Distributed Based Upon The Proportion Of Dropouts In The School District To The Total Number Of Dropouts In This State; To Provide That A School District May Receive Adequate Education Program Funds For Students Enrolled In A Hope Program If Certain Criteria Are Met; To Specify Categories Of Programming In The Hope Program; To Specify The Minimum Components For Programs To Be Funded Through The Hope Program; And For Related Purposes.</description><committee/><history><step><date>2014-01-13</date><action>Referred To Education;Appropriations</action><chamber>H</chamber><chamber_id>57</chamber_id><importance>1</importance></step><step><date>2014-02-04</date><action>Died In Committee</action><chamber>H</chamber><chamber_id>57</chamber_id><importance>1</importance></step></history><sponsors><sponsor><people_id>6524</people_id><name>Omeria Scott</name><role_id>1</role_id><ftm_id>0</ftm_id><sponsor_type_id>1</sponsor_type_id><sponsor_order>1</sponsor_order></sponsor></sponsors><texts><text><doc_id>912184</doc_id><date>2014-01-13</date><type>Introduced</type><mime>text/html</mime><url>http://legiscan.com/MS/text/HB151/id/912184</url><state_link>http://billstatus.ls.state.ms.us/documents/2014/html/HB/0100-0199/HB0151IN.htm</state_link></text></texts></bill></legiscan>
