<?xml version="1.0" encoding="UTF-8"?>
<legiscan><status></status><bill><bill_id>598294</bill_id><change_hash>48522d61ff9bc3533e7709e9d3fb9f55</change_hash><session><session_id>1083</session_id><session_name>2014 Regular Session</session_name></session><url>http://legiscan.com/MS/bill/HB368/2014</url><state_link>http://billstatus.ls.state.ms.us/2014/pdf/history/HB/HB0368.xml</state_link><completed>1</completed><status>6</status><status_date>2014-02-04</status_date><progress><step><date>2014-01-20</date><event>1</event></step><step><date>2014-01-20</date><event>9</event></step><step><date>2014-02-04</date><event>6</event></step></progress><state>MS</state><state_id>24</state_id><bill_number>HB368</bill_number><bill_type>B</bill_type><body>H</body><body_id>57</body_id><current_body>H</current_body><current_body_id>57</current_body_id><title>Youth found to be in possession of drugs, certain; require to attend drug court program.</title><description>An Act To Amend Section 9-23-15, Mississippi Code Of 1972, To Provide That If Any Youth Is Found In Possession Of Illegal Drugs Or Drug Paraphernalia On School Property Then Such Youth Shall Be Ordered By A Youth Court Judge To Participate In A Drug Court Program; To Require The Record Of Such Youth To Be Expunged Upon The Completion Of A Drug Court Program; To Amend Section 43-21-605, Mississippi Code Of 1972, In Conformity Thereto; And For Related Purposes.</description><committee/><history><step><date>2014-01-20</date><action>Referred To Judiciary B</action><chamber>H</chamber><chamber_id>57</chamber_id><importance>1</importance></step><step><date>2014-02-04</date><action>Died In Committee</action><chamber>H</chamber><chamber_id>57</chamber_id><importance>1</importance></step></history><sponsors><sponsor><people_id>13808</people_id><name>Deborah Butler Dixon</name><role_id>1</role_id><ftm_id>0</ftm_id><sponsor_type_id>1</sponsor_type_id><sponsor_order>1</sponsor_order></sponsor></sponsors><texts><text><doc_id>929161</doc_id><date>2014-01-20</date><type>Introduced</type><mime>text/html</mime><url>http://legiscan.com/MS/text/HB368/id/929161</url><state_link>http://billstatus.ls.state.ms.us/documents/2014/html/HB/0300-0399/HB0368IN.htm</state_link></text></texts></bill></legiscan>
