<?xml version="1.0" encoding="UTF-8"?>
<legiscan><status></status><bill><bill_id>598398</bill_id><change_hash>3280bb0ceed9b5751ba53ae0d6ec8d60</change_hash><session><session_id>1083</session_id><session_name>2014 Regular Session</session_name></session><url>http://legiscan.com/MS/bill/HB472/2014</url><state_link>http://billstatus.ls.state.ms.us/2014/pdf/history/HB/HB0472.xml</state_link><completed>1</completed><status>6</status><status_date>2014-02-04</status_date><progress><step><date>2014-01-20</date><event>1</event></step><step><date>2014-01-20</date><event>9</event></step><step><date>2014-02-04</date><event>6</event></step></progress><state>MS</state><state_id>24</state_id><bill_number>HB472</bill_number><bill_type>B</bill_type><body>H</body><body_id>57</body_id><current_body>H</current_body><current_body_id>57</current_body_id><title>State parks; require Department of Wildlife, Fisheries and Parks to provide Wi-Fi access in all.</title><description>An Act To Require The Mississippi Department Of Wildlife, Fisheries And Parks, With The Approval Of The Commission On Wildlife, Fisheries And Parks, To Identify Certain Areas Within State Parks For The Installation Of Equipment To Provide Wireless Internet (wi-fi) Access To Patrons Of The Parks; To Require The Commission To Establish Criteria For Identifying Such Areas; To Require The Department, With Approval Of The Commission, To Enter Into Contracts Or Agreements With A Service Provider For The Purpose Of Installing, Maintaining And Servicing Any Equipment That Provides Wireless Internet (wi-fi) Access; To Amend Section 55-3-33, Mississippi Code Of 1972, In Conformity To The Preceding Provisions; And For Related Purposes.</description><committee/><history><step><date>2014-01-20</date><action>Referred To Wildlife, Fisheries and Parks;Public Property</action><chamber>H</chamber><chamber_id>57</chamber_id><importance>1</importance></step><step><date>2014-02-04</date><action>Died In Committee</action><chamber>H</chamber><chamber_id>57</chamber_id><importance>1</importance></step></history><sponsors><sponsor><people_id>13799</people_id><name>Tom Miles</name><role_id>1</role_id><ftm_id>0</ftm_id><sponsor_type_id>1</sponsor_type_id><sponsor_order>1</sponsor_order></sponsor></sponsors><texts><text><doc_id>929257</doc_id><date>2014-01-20</date><type>Introduced</type><mime>text/html</mime><url>http://legiscan.com/MS/text/HB472/id/929257</url><state_link>http://billstatus.ls.state.ms.us/documents/2014/html/HB/0400-0499/HB0472IN.htm</state_link></text></texts></bill></legiscan>
