<?xml version="1.0" encoding="UTF-8"?>
<legiscan><status></status><bill><bill_id>577846</bill_id><change_hash>a5e6303aeb46b49c6d914d36b4d52d3c</change_hash><session><session_id>1083</session_id><session_name>2014 Regular Session</session_name></session><url>http://legiscan.com/MS/bill/HC1/2014</url><state_link>http://billstatus.ls.state.ms.us/2014/pdf/history/HC/HC0001.xml</state_link><completed>1</completed><status>6</status><status_date>2014-04-02</status_date><progress><step><date>2014-01-07</date><event>1</event></step><step><date>2014-01-07</date><event>9</event></step><step><date>2014-04-02</date><event>6</event></step></progress><state>MS</state><state_id>24</state_id><bill_number>HC1</bill_number><bill_type>CR</bill_type><body>H</body><body_id>57</body_id><current_body>H</current_body><current_body_id>57</current_body_id><title>United States Pledge of Allegiance; commemorate 60th anniversary of addition of the phase &quot;under God&quot; to.</title><description>A Concurrent Resolution Commemorating And Recognizing The 60th Anniversary Of The Addition Of The Phrase &quot;under God&quot; To The United States Pledge Of Allegiance And Reminding American Citizens Of The Christian Principles That America Was Founded Upon.</description><committee/><history><step><date>2014-01-07</date><action>Referred To Rules</action><chamber>H</chamber><chamber_id>57</chamber_id><importance>1</importance></step><step><date>2014-04-02</date><action>Died In Committee</action><chamber>H</chamber><chamber_id>57</chamber_id><importance>1</importance></step></history><sponsors><sponsor><people_id>13801</people_id><name>Randal Rushing</name><role_id>1</role_id><ftm_id>0</ftm_id><sponsor_type_id>1</sponsor_type_id><sponsor_order>1</sponsor_order></sponsor><sponsor><people_id>13799</people_id><name>Tom Miles</name><role_id>1</role_id><ftm_id>0</ftm_id><sponsor_type_id>1</sponsor_type_id><sponsor_order>2</sponsor_order></sponsor></sponsors><texts><text><doc_id>906242</doc_id><date>2014-01-07</date><type>Introduced</type><mime>text/html</mime><url>http://legiscan.com/MS/text/HC1/id/906242</url><state_link>http://billstatus.ls.state.ms.us/documents/2014/html/HC/HC0001IN.htm</state_link></text></texts></bill></legiscan>
