<?xml version="1.0" encoding="UTF-8"?>
<legiscan><status></status><bill><bill_id>581890</bill_id><change_hash>78d61f219b02c36cd0b85f09913b2bda</change_hash><session><session_id>1083</session_id><session_name>2014 Regular Session</session_name></session><url>http://legiscan.com/MS/bill/SB2080/2014</url><state_link>http://billstatus.ls.state.ms.us/2014/pdf/history/SB/SB2080.xml</state_link><completed>1</completed><status>6</status><status_date>2014-02-26</status_date><progress><step><date>2014-01-10</date><event>1</event></step><step><date>2014-01-10</date><event>9</event></step><step><date>2014-02-26</date><event>6</event></step></progress><state>MS</state><state_id>24</state_id><bill_number>SB2080</bill_number><bill_type>B</bill_type><body>S</body><body_id>58</body_id><current_body>S</current_body><current_body_id>58</current_body_id><title>Distinguished Flying Cross, Air Medal and the Bronze Star motor vehicle tags; exempt from vehicle registration fees and taxes.</title><description>An Act To Amend Sections 27-19-56.13 And 27-19-56.62, Mississippi Code Of 1972, To Provide That The Distinctive Motor Vehicle License Tag Authorized To Be Issued To Recipients Of The Distinguished Flying Cross, The Air Medal And The Bronze Star Shall Be Exempt From All Motor Vehicle Registration Fees And Privilege Taxes; To Provide That The Surviving Spouse Of A Deceased Person Who Was Issued Such A License Plate Or Tag Shall Be Entitled To Apply For Or Retain Such A License Plate Or Tag Issued Under This Section And May Continue Annually To Renew Registration For One Such Motor Vehicle License Plate Or Tag For As Long As The Spouse Remains Unremarried; To Amend Section 27-51-41, Mississippi Code Of 1972, To Exempt From Ad Valorem Taxation Certain Motor Vehicles Owned By; And For Related Purposes.</description><committee/><history><step><date>2014-01-10</date><action>Referred To Finance</action><chamber>S</chamber><chamber_id>58</chamber_id><importance>1</importance></step><step><date>2014-02-26</date><action>Died In Committee</action><chamber>S</chamber><chamber_id>58</chamber_id><importance>1</importance></step></history><sponsors><sponsor><people_id>14359</people_id><name>David Parker</name><role_id>2</role_id><ftm_id>0</ftm_id><sponsor_type_id>1</sponsor_type_id><sponsor_order>1</sponsor_order></sponsor></sponsors><texts><text><doc_id>910426</doc_id><date>2014-01-10</date><type>Introduced</type><mime>text/html</mime><url>http://legiscan.com/MS/text/SB2080/id/910426</url><state_link>http://billstatus.ls.state.ms.us/documents/2014/html/SB/2001-2099/SB2080IN.htm</state_link></text></texts></bill></legiscan>
