<?xml version="1.0" encoding="UTF-8"?>
<legiscan><status></status><bill><bill_id>601516</bill_id><change_hash>e133c07be0ae6437fef09bc2cabdea76</change_hash><session><session_id>1083</session_id><session_name>2014 Regular Session</session_name></session><url>http://legiscan.com/MS/bill/SB2717/2014</url><state_link>http://billstatus.ls.state.ms.us/2014/pdf/history/SB/SB2717.xml</state_link><completed>0</completed><status>6</status><status_date>2014-03-27</status_date><progress><step><date>2014-01-20</date><event>1</event></step><step><date>2014-01-20</date><event>9</event></step><step><date>2014-02-05</date><event>2</event></step><step><date>2014-02-15</date><event>9</event></step><step><date>2014-03-27</date><event>6</event></step></progress><state>MS</state><state_id>24</state_id><bill_number>SB2717</bill_number><bill_type>B</bill_type><body>S</body><body_id>58</body_id><current_body>H</current_body><current_body_id>57</current_body_id><title>Executive Committee; prohibit certain persons from serving on municipal, county and state.</title><description>An Act To Amend Section 25-1-115, Mississippi Code Of 1972, To Prohibit Any Person Who Has Been Convicted Of Any Felony In This State Or In Any Other State From Serving On Any Municipal Executive Committee, County Executive Committee Or State Executive Committee; To Prohibit Any Person Who Has Been Convicted Of Any State Or Federal Election Crime In This State Or In Any Other State From Serving On Any Municipal Executive Committee, County Executive Committee Or State Executive Committee; And For Related Purposes.</description><committee/><history><step><date>2014-01-20</date><action>Referred To Judiciary, Division B</action><chamber>S</chamber><chamber_id>58</chamber_id><importance>1</importance></step><step><date>2014-02-04</date><action>Title Suff Do Pass</action><chamber>S</chamber><chamber_id>58</chamber_id><importance>0</importance></step><step><date>2014-02-05</date><action>Passed</action><chamber>S</chamber><chamber_id>58</chamber_id><importance>1</importance></step><step><date>2014-02-06</date><action>Transmitted To House</action><chamber>S</chamber><chamber_id>58</chamber_id><importance>0</importance></step><step><date>2014-02-15</date><action>Referred To Apportionment and Elections</action><chamber>H</chamber><chamber_id>57</chamber_id><importance>1</importance></step><step><date>2014-03-04</date><action>Title Suff Do Pass As Amended</action><chamber>H</chamber><chamber_id>57</chamber_id><importance>0</importance></step><step><date>2014-03-11</date><action>Read the Third Time</action><chamber>H</chamber><chamber_id>57</chamber_id><importance>0</importance></step><step><date>2014-03-12</date><action>Amended</action><chamber>H</chamber><chamber_id>57</chamber_id><importance>0</importance></step><step><date>2014-03-12</date><action>Passed As Amended</action><chamber>H</chamber><chamber_id>57</chamber_id><importance>0</importance></step><step><date>2014-03-13</date><action>Returned For Concurrence</action><chamber>H</chamber><chamber_id>57</chamber_id><importance>0</importance></step><step><date>2014-03-27</date><action>Died On Calendar</action><chamber>S</chamber><chamber_id>58</chamber_id><importance>1</importance></step></history><sponsors><sponsor><people_id>13662</people_id><name>Josh Harkins</name><role_id>2</role_id><ftm_id>0</ftm_id><sponsor_type_id>1</sponsor_type_id><sponsor_order>1</sponsor_order></sponsor></sponsors><texts><text><doc_id>932319</doc_id><date>2014-01-22</date><type>Introduced</type><mime>text/html</mime><url>http://legiscan.com/MS/text/SB2717/id/932319</url><state_link>http://billstatus.ls.state.ms.us/documents/2014/html/SB/2700-2799/SB2717IN.htm</state_link></text><text><doc_id>950972</doc_id><date>2014-02-06</date><type>Engrossed</type><mime>text/html</mime><url>http://legiscan.com/MS/text/SB2717/id/950972</url><state_link>http://billstatus.ls.state.ms.us/documents/2014/html/SB/2700-2799/SB2717PS.htm</state_link></text></texts><votes><vote><roll_call_id>316220</roll_call_id><date>2014-02-05</date><passed>1</passed><desc>Senate Passed</desc><url>http://legiscan.com/MS/rollcall/SB2717/id/316220</url><state_link>http://billstatus.ls.state.ms.us/2014/pdf/votes/senate/0300053.pdf</state_link></vote><vote><roll_call_id>340441</roll_call_id><date>2014-03-12</date><passed>1</passed><desc>House Passed As Amended</desc><url>http://legiscan.com/MS/rollcall/SB2717/id/340441</url><state_link>http://billstatus.ls.state.ms.us/2014/pdf/votes/house/0650011.pdf</state_link></vote></votes></bill></legiscan>
