<?xml version="1.0" encoding="UTF-8"?>
<legiscan><status></status><bill><bill_id>229207</bill_id><change_hash>06ba36aad953c68be1be4aa06db77fa3</change_hash><session><session_id>87</session_id><session_name>2011 Regular Session</session_name></session><url>http://legiscan.com/MS/bill/HB849/2011</url><state_link>http://billstatus.ls.state.ms.us/2011/pdf/history/HB/HB0849.xml</state_link><completed>1</completed><status>6</status><status_date>2011-02-01</status_date><progress><step><date>2011-01-17</date><event>1</event></step><step><date>2011-01-17</date><event>9</event></step><step><date>2011-02-01</date><event>6</event></step></progress><state>MS</state><state_id>24</state_id><bill_number>HB849</bill_number><bill_type>B</bill_type><body>H</body><body_id>57</body_id><current_body>H</current_body><current_body_id>57</current_body_id><title>Driver's license; provide that original and renewal will expire after six years and prescribe fee for.</title><description>An Act To Amend Section 63-1-43, Mississippi Code Of 1972, To Prescribe The Fee For A Six-year Driver's License; To Amend Section 63-1-47, Mississippi Code Of 1972, To Provide That Each Applicant For An Original Or Renewal License Shall Be Provided A Six-year License Unless Otherwise Provided By Law; To Amend Section 63-1-49, Mississippi Code Of 1972, To Allow A Person Who Is Going Overseas, And Whose License Will Expire Overseas, To Renew His License For Six Years Before Leaving; And For Related Purposes.</description><committee/><history><step><date>2011-01-17</date><action>Referred To Transportation</action><chamber></chamber><chamber_id>0</chamber_id><importance>1</importance></step><step><date>2011-02-01</date><action>Died In Committee</action><chamber></chamber><chamber_id>0</chamber_id><importance>1</importance></step></history><sponsors><sponsor><people_id>6498</people_id><name>Charles Beckett</name><role_id>1</role_id><ftm_id>5850</ftm_id><sponsor_type_id>0</sponsor_type_id><sponsor_order>0</sponsor_order></sponsor></sponsors><texts><text><doc_id>238535</doc_id><date>2011-01-17</date><type>Introduced</type><mime>text/html</mime><url>http://legiscan.com/MS/text/HB849/id/238535</url><state_link>http://billstatus.ls.state.ms.us/documents/2011/html/HB/0800-0899/HB0849IN.htm</state_link></text></texts></bill></legiscan>
