<?xml version="1.0" encoding="UTF-8"?>
<legiscan><status></status><bill><bill_id>316322</bill_id><change_hash>8b151d643c9ef0275bb20966dca0acd3</change_hash><session><session_id>87</session_id><session_name>2011 Regular Session</session_name></session><url>http://legiscan.com/MS/bill/HR70/2011</url><state_link>http://billstatus.ls.state.ms.us/2011/pdf/history/HR/HR0070.xml</state_link><completed>1</completed><status>4</status><status_date>2011-03-21</status_date><progress><step><date>2011-03-17</date><event>1</event></step><step><date>2011-03-17</date><event>9</event></step><step><date>2011-03-17</date><event>2</event></step><step><date>2011-03-21</date><event>3</event></step><step><date>2011-03-21</date><event>4</event></step></progress><state>MS</state><state_id>24</state_id><bill_number>HR70</bill_number><bill_type>R</bill_type><body>H</body><body_id>57</body_id><current_body>H</current_body><current_body_id>57</current_body_id><title>Mr. Porter &quot;Bo Dollar&quot; Hubbard; commend life and legacy upon his passing.</title><description>A Resolution Commending The Life And Legacy Of Mr. Porter &quot;bo Dollar&quot; Hubbard And Expressing Deepest Sympathy To His Family And Friends Upon His Passing.</description><committee/><history><step><date>2011-03-17</date><action>Referred To Rules</action><chamber></chamber><chamber_id>0</chamber_id><importance>1</importance></step><step><date>2011-03-17</date><action>Title Suff Do Be Adopted</action><chamber></chamber><chamber_id>0</chamber_id><importance>0</importance></step><step><date>2011-03-17</date><action>Adopted</action><chamber></chamber><chamber_id>0</chamber_id><importance>1</importance></step><step><date>2011-03-17</date><action>Immediate Release</action><chamber></chamber><chamber_id>0</chamber_id><importance>0</importance></step><step><date>2011-03-21</date><action>Enrolled Bill Signed</action><chamber></chamber><chamber_id>0</chamber_id><importance>1</importance></step></history><sponsors><sponsor><people_id>6503</people_id><name>Karl Gibbs</name><role_id>1</role_id><ftm_id>408</ftm_id><sponsor_type_id>0</sponsor_type_id><sponsor_order>0</sponsor_order></sponsor><sponsor><people_id>6511</people_id><name>Gary Chism</name><role_id>1</role_id><ftm_id>3613</ftm_id><sponsor_type_id>0</sponsor_type_id><sponsor_order>0</sponsor_order></sponsor><sponsor><people_id>6606</people_id><name>Esther Harrison</name><role_id>1</role_id><ftm_id>3595</ftm_id><sponsor_type_id>0</sponsor_type_id><sponsor_order>0</sponsor_order></sponsor><sponsor><people_id>6610</people_id><name>Tyrone Ellis</name><role_id>1</role_id><ftm_id>0</ftm_id><sponsor_type_id>0</sponsor_type_id><sponsor_order>0</sponsor_order></sponsor><sponsor><people_id>6612</people_id><name>Jeffrey Smith</name><role_id>1</role_id><ftm_id>0</ftm_id><sponsor_type_id>0</sponsor_type_id><sponsor_order>0</sponsor_order></sponsor></sponsors><texts><text><doc_id>264783</doc_id><date>2011-03-17</date><type>Introduced</type><mime>text/html</mime><url>http://legiscan.com/MS/text/HR70/id/264783</url><state_link>http://billstatus.ls.state.ms.us/documents/2011/html/HR/HR0070IN.htm</state_link></text><text><doc_id>264784</doc_id><date>2011-03-17</date><type>Engrossed</type><mime>text/html</mime><url>http://legiscan.com/MS/text/HR70/id/264784</url><state_link>http://billstatus.ls.state.ms.us/documents/2011/html/HR/HR0070PS.htm</state_link></text></texts></bill></legiscan>
