<?xml version="1.0" encoding="UTF-8"?>
<legiscan><status></status><bill><bill_id>260669</bill_id><change_hash>2d6488417b6a2ddfe0bf1808850dae7d</change_hash><session><session_id>87</session_id><session_name>2011 Regular Session</session_name></session><url>http://legiscan.com/MS/bill/SB3025/2011</url><state_link>http://billstatus.ls.state.ms.us/2011/pdf/history/SB/SB3025.xml</state_link><completed>1</completed><status>4</status><status_date>2011-04-04</status_date><progress><step><date>2011-02-08</date><event>1</event></step><step><date>2011-02-08</date><event>9</event></step><step><date>2011-03-15</date><event>2</event></step><step><date>2011-03-16</date><event>9</event></step><step><date>2011-03-26</date><event>3</event></step><step><date>2011-04-04</date><event>4</event></step></progress><state>MS</state><state_id>24</state_id><bill_number>SB3025</bill_number><bill_type>B</bill_type><body>S</body><body_id>58</body_id><current_body>S</current_body><current_body_id>58</current_body_id><title>Forrest County; authorize contributions to various organizations.</title><description>An Act To Authorize The Board Of Supervisors Of Forrest County To Contribute Funds To The Association For Retarded Citizens, Big Brothers/big Sisters Of Southeast Mississippi, The Boy Scouts Of America, The Gulf Pine Girl Scout Council, The Hattiesburg Downtown Association, Inc., The Neighborhood Education Enhancement Development Services, The Salvation Army, Pearl River Valley Opportunity, The Pinebelt Association For Community Enhancement, The Hattiesburg Little League Baseball Association, Petal Optimist Club Baseball, First Tee And The Aids Services Coalition; And For Related Purposes.</description><committee/><history><step><date>2011-02-08</date><action>Referred To Local and Private</action><chamber></chamber><chamber_id>0</chamber_id><importance>1</importance></step><step><date>2011-03-14</date><action>Title Suff Do Pass</action><chamber></chamber><chamber_id>0</chamber_id><importance>0</importance></step><step><date>2011-03-15</date><action>Passed</action><chamber></chamber><chamber_id>0</chamber_id><importance>1</importance></step><step><date>2011-03-15</date><action>Immediate Release</action><chamber></chamber><chamber_id>0</chamber_id><importance>0</importance></step><step><date>2011-03-15</date><action>Transmitted To House</action><chamber></chamber><chamber_id>0</chamber_id><importance>0</importance></step><step><date>2011-03-16</date><action>Referred To Local and Private Legislation</action><chamber></chamber><chamber_id>0</chamber_id><importance>1</importance></step><step><date>2011-03-24</date><action>Title Suff Do Pass</action><chamber></chamber><chamber_id>0</chamber_id><importance>0</importance></step><step><date>2011-03-25</date><action>Passed</action><chamber></chamber><chamber_id>0</chamber_id><importance>0</importance></step><step><date>2011-03-25</date><action>Immediate Release</action><chamber></chamber><chamber_id>0</chamber_id><importance>0</importance></step><step><date>2011-03-25</date><action>Transmitted To Senate</action><chamber></chamber><chamber_id>0</chamber_id><importance>0</importance></step><step><date>2011-03-26</date><action>Enrolled Bill Signed</action><chamber></chamber><chamber_id>0</chamber_id><importance>1</importance></step><step><date>2011-03-27</date><action>Enrolled Bill Signed</action><chamber></chamber><chamber_id>0</chamber_id><importance>0</importance></step><step><date>2011-04-04</date><action>Approved by Governor</action><chamber></chamber><chamber_id>0</chamber_id><importance>1</importance></step></history><sponsors><sponsor><people_id>6631</people_id><name>Billy Hudson</name><role_id>2</role_id><ftm_id>0</ftm_id><sponsor_type_id>0</sponsor_type_id><sponsor_order>0</sponsor_order></sponsor></sponsors><texts><text><doc_id>138965</doc_id><date>2011-02-08</date><type>Introduced</type><mime>text/html</mime><url>http://legiscan.com/MS/text/SB3025/id/138965</url><state_link>http://billstatus.ls.state.ms.us/documents/2011/html/SB/3000-3099/SB3025IN.htm</state_link></text><text><doc_id>223760</doc_id><date>2011-03-15</date><type>Engrossed</type><mime>text/html</mime><url>http://legiscan.com/MS/text/SB3025/id/223760</url><state_link>http://billstatus.ls.state.ms.us/documents/2011/html/SB/3000-3099/SB3025PS.htm</state_link></text><text><doc_id>228725</doc_id><date>2011-03-26</date><type>Enrolled</type><mime>text/html</mime><url>http://legiscan.com/MS/text/SB3025/id/228725</url><state_link>http://billstatus.ls.state.ms.us/documents/2011/html/SB/3000-3099/SB3025SG.htm</state_link></text></texts><votes><vote><roll_call_id>67317</roll_call_id><date>2011-03-15</date><passed>1</passed><desc>Senate Passed</desc><url>http://legiscan.com/MS/rollcall/SB3025/id/67317</url><state_link>http://billstatus.ls.state.ms.us/2011/pdf/votes/senate/0710005.pdf</state_link></vote><vote><roll_call_id>67318</roll_call_id><date>2011-03-25</date><passed>1</passed><desc>House Passed</desc><url>http://legiscan.com/MS/rollcall/SB3025/id/67318</url><state_link>http://billstatus.ls.state.ms.us/2011/pdf/votes/house/0810005.pdf</state_link></vote></votes></bill></legiscan>
