<?xml version="1.0" encoding="UTF-8"?>
<legiscan><status></status><bill><bill_id>311768</bill_id><change_hash>d90e1a59a9b1b7142f0209cc5bbdbf07</change_hash><session><session_id>87</session_id><session_name>2011 Regular Session</session_name></session><url>http://legiscan.com/MS/bill/SB3125/2011</url><state_link>http://billstatus.ls.state.ms.us/2011/pdf/history/SB/SB3125.xml</state_link><completed>0</completed><status>4</status><status_date>2011-04-06</status_date><progress><step><date>2011-03-18</date><event>1</event></step><step><date>2011-03-18</date><event>9</event></step><step><date>2011-03-23</date><event>2</event></step><step><date>2011-03-24</date><event>9</event></step><step><date>2011-03-30</date><event>3</event></step><step><date>2011-04-06</date><event>4</event></step></progress><state>MS</state><state_id>24</state_id><bill_number>SB3125</bill_number><bill_type>B</bill_type><body>S</body><body_id>58</body_id><current_body>S</current_body><current_body_id>58</current_body_id><title>Warren County; authorize contributions to various organizations.</title><description>An Act To Authorize The Board Of Supervisors Of Warren County, Mississippi, To Contribute Funds To Central Mississippi Prevention Services, Inc.; Mississippi Food Network; The Initiative, Inc.; Triumph Ministries, Inc.; Vicksburg Family Development Services, Inc.; Vicksburg Main Street Project; Warren Washington Issaquena Sharkey Community Action Agency, Inc.; We Care Community Services, Inc.; And Women's Restoration Shelter Of Mountain Faith Ministries; And For Related Purposes.</description><committee/><history><step><date>2011-03-18</date><action>Referred To Local and Private</action><chamber></chamber><chamber_id>0</chamber_id><importance>1</importance></step><step><date>2011-03-22</date><action>Title Suff Do Pass</action><chamber></chamber><chamber_id>0</chamber_id><importance>0</importance></step><step><date>2011-03-23</date><action>Passed</action><chamber></chamber><chamber_id>0</chamber_id><importance>1</importance></step><step><date>2011-03-23</date><action>Immediate Release</action><chamber></chamber><chamber_id>0</chamber_id><importance>0</importance></step><step><date>2011-03-23</date><action>Transmitted To House</action><chamber></chamber><chamber_id>0</chamber_id><importance>0</importance></step><step><date>2011-03-24</date><action>Referred To Local and Private Legislation</action><chamber></chamber><chamber_id>0</chamber_id><importance>1</importance></step><step><date>2011-03-26</date><action>Title Suff Do Pass</action><chamber></chamber><chamber_id>0</chamber_id><importance>0</importance></step><step><date>2011-03-27</date><action>Passed</action><chamber></chamber><chamber_id>0</chamber_id><importance>0</importance></step><step><date>2011-03-27</date><action>Immediate Release</action><chamber></chamber><chamber_id>0</chamber_id><importance>0</importance></step><step><date>2011-03-27</date><action>Transmitted To Senate</action><chamber></chamber><chamber_id>0</chamber_id><importance>0</importance></step><step><date>2011-03-30</date><action>Enrolled Bill Signed</action><chamber></chamber><chamber_id>0</chamber_id><importance>1</importance></step><step><date>2011-03-30</date><action>Enrolled Bill Signed</action><chamber></chamber><chamber_id>0</chamber_id><importance>0</importance></step><step><date>2011-04-06</date><action>Approved by Governor</action><chamber></chamber><chamber_id>0</chamber_id><importance>1</importance></step></history><sponsors><sponsor><people_id>6660</people_id><name>Briggs Hopson</name><role_id>2</role_id><ftm_id>9007</ftm_id><sponsor_type_id>0</sponsor_type_id><sponsor_order>0</sponsor_order></sponsor></sponsors><texts><text><doc_id>259250</doc_id><date>2011-03-18</date><type>Introduced</type><mime>text/html</mime><url>http://legiscan.com/MS/text/SB3125/id/259250</url><state_link>http://billstatus.ls.state.ms.us/documents/2011/html/SB/3100-3199/SB3125IN.htm</state_link></text><text><doc_id>259251</doc_id><date>2011-03-23</date><type>Engrossed</type><mime>text/html</mime><url>http://legiscan.com/MS/text/SB3125/id/259251</url><state_link>http://billstatus.ls.state.ms.us/documents/2011/html/SB/3100-3199/SB3125PS.htm</state_link></text><text><doc_id>259252</doc_id><date>2011-03-30</date><type>Enrolled</type><mime>text/html</mime><url>http://legiscan.com/MS/text/SB3125/id/259252</url><state_link>http://billstatus.ls.state.ms.us/documents/2011/html/SB/3100-3199/SB3125SG.htm</state_link></text></texts><votes><vote><roll_call_id>71144</roll_call_id><date>2011-03-23</date><passed>1</passed><desc>Senate Passed</desc><url>http://legiscan.com/MS/rollcall/SB3125/id/71144</url><state_link>http://billstatus.ls.state.ms.us/2011/pdf/votes/senate/0790005.pdf</state_link></vote><vote><roll_call_id>71145</roll_call_id><date>2011-03-27</date><passed>1</passed><desc>House Passed</desc><url>http://legiscan.com/MS/rollcall/SB3125/id/71145</url><state_link>http://billstatus.ls.state.ms.us/2011/pdf/votes/house/0830013.pdf</state_link></vote></votes></bill></legiscan>
