<?xml version="1.0" encoding="UTF-8"?>
<legiscan><status></status><bill><bill_id>225108</bill_id><change_hash>6cf02b4412e1b28168442c4e3865d453</change_hash><session><session_id>87</session_id><session_name>2011 Regular Session</session_name></session><url>http://legiscan.com/MS/bill/SC503/2011</url><state_link>http://billstatus.ls.state.ms.us/2011/pdf/history/SC/SC0503.xml</state_link><completed>1</completed><status>6</status><status_date>2011-04-07</status_date><progress><step><date>2011-01-04</date><event>1</event></step><step><date>2011-01-04</date><event>9</event></step><step><date>2011-04-07</date><event>6</event></step></progress><state>MS</state><state_id>24</state_id><bill_number>SC503</bill_number><bill_type>CR</bill_type><body>S</body><body_id>58</body_id><current_body>S</current_body><current_body_id>58</current_body_id><title>United States Constitution; urge Congress to call convention to amend relative to a flat-rate income tax system.</title><description>A Concurrent Resolution Requesting The Congress Of The United States To Call A Convention For The Sole Purpose Of Proposing An Amendment To The Constitution Of The United States Relating To A Flat-rate Income Tax System And Urging And Requesting The Legislative Bodies Of The Several States To Apply To The Congress To Call Such A Convention.</description><committee/><history><step><date>2011-01-04</date><action>Referred To Rules</action><chamber></chamber><chamber_id>0</chamber_id><importance>1</importance></step><step><date>2011-04-07</date><action>Died In Committee</action><chamber></chamber><chamber_id>0</chamber_id><importance>1</importance></step></history><sponsors><sponsor><people_id>6637</people_id><name>Dean Kirby</name><role_id>2</role_id><ftm_id>376</ftm_id><sponsor_type_id>0</sponsor_type_id><sponsor_order>0</sponsor_order></sponsor></sponsors><texts><text><doc_id>145127</doc_id><date>2011-01-04</date><type>Introduced</type><mime>text/html</mime><url>http://legiscan.com/MS/text/SC503/id/145127</url><state_link>http://billstatus.ls.state.ms.us/documents/2011/html/SC/SC0503IN.htm</state_link></text></texts></bill></legiscan>
